{
  "schemaVersion": 1,
  "feedId": "fx",
  "ssotUrl": "http://localhost:3000/api/fx/config",
  "ssotSource": "frontend",
  "provenance": {
    "ssotVersion": 1,
    "ssotHash": "ce61c0cb60f7a79cd15f556580910fef87ce01101fecebfd22b7893826ad5e65",
    "ssotFingerprint": "ce61c0cb60f7",
    "snapshotAt": "2026-01-15T18:12:48.608Z"
  },
  "catalog": [
    {
      "id": "eur-usd",
      "base": "EUR",
      "quote": "USD",
      "isDefaultFree": true,
      "isDefaultPaid": true
    },
    {
      "id": "usd-jpy",
      "base": "USD",
      "quote": "JPY",
      "isDefaultFree": true,
      "isDefaultPaid": true
    },
    {
      "id": "gbp-usd",
      "base": "GBP",
      "quote": "USD",
      "isDefaultFree": true,
      "isDefaultPaid": true
    },
    {
      "id": "aud-usd",
      "base": "AUD",
      "quote": "USD",
      "isDefaultFree": false,
      "isDefaultPaid": false
    },
    {
      "id": "nzd-usd",
      "base": "NZD",
      "quote": "USD",
      "isDefaultFree": false,
      "isDefaultPaid": false
    },
    {
      "id": "usd-cad",
      "base": "USD",
      "quote": "CAD",
      "isDefaultFree": false,
      "isDefaultPaid": false
    },
    {
      "id": "usd-chf",
      "base": "USD",
      "quote": "CHF",
      "isDefaultFree": false,
      "isDefaultPaid": false
    },
    {
      "id": "usd-cnh",
      "base": "USD",
      "quote": "CNH",
      "isDefaultFree": false,
      "isDefaultPaid": false
    },
    {
      "id": "usd-cny",
      "base": "USD",
      "quote": "CNY",
      "isDefaultFree": true,
      "isDefaultPaid": true
    },
    {
      "id": "usd-hkd",
      "base": "USD",
      "quote": "HKD",
      "isDefaultFree": false,
      "isDefaultPaid": false
    },
    {
      "id": "usd-sgd",
      "base": "USD",
      "quote": "SGD",
      "isDefaultFree": false,
      "isDefaultPaid": false
    },
    {
      "id": "usd-krw",
      "base": "USD",
      "quote": "KRW",
      "isDefaultFree": false,
      "isDefaultPaid": false
    },
    {
      "id": "usd-sek",
      "base": "USD",
      "quote": "SEK",
      "isDefaultFree": false,
      "isDefaultPaid": false
    },
    {
      "id": "usd-nok",
      "base": "USD",
      "quote": "NOK",
      "isDefaultFree": false,
      "isDefaultPaid": false
    },
    {
      "id": "usd-dkk",
      "base": "USD",
      "quote": "DKK",
      "isDefaultFree": false,
      "isDefaultPaid": false
    },
    {
      "id": "usd-inr",
      "base": "USD",
      "quote": "INR",
      "isDefaultFree": false,
      "isDefaultPaid": false
    },
    {
      "id": "usd-twd",
      "base": "USD",
      "quote": "TWD",
      "isDefaultFree": false,
      "isDefaultPaid": false
    },
    {
      "id": "usd-thb",
      "base": "USD",
      "quote": "THB",
      "isDefaultFree": false,
      "isDefaultPaid": false
    },
    {
      "id": "usd-myr",
      "base": "USD",
      "quote": "MYR",
      "isDefaultFree": false,
      "isDefaultPaid": false
    },
    {
      "id": "usd-idr",
      "base": "USD",
      "quote": "IDR",
      "isDefaultFree": false,
      "isDefaultPaid": false
    },
    {
      "id": "usd-php",
      "base": "USD",
      "quote": "PHP",
      "isDefaultFree": false,
      "isDefaultPaid": false
    },
    {
      "id": "usd-vnd",
      "base": "USD",
      "quote": "VND",
      "isDefaultFree": false,
      "isDefaultPaid": false
    },
    {
      "id": "usd-mxn",
      "base": "USD",
      "quote": "MXN",
      "isDefaultFree": false,
      "isDefaultPaid": false
    },
    {
      "id": "usd-brl",
      "base": "USD",
      "quote": "BRL",
      "isDefaultFree": true,
      "isDefaultPaid": true
    },
    {
      "id": "usd-zar",
      "base": "USD",
      "quote": "ZAR",
      "isDefaultFree": false,
      "isDefaultPaid": false
    },
    {
      "id": "usd-try",
      "base": "USD",
      "quote": "TRY",
      "isDefaultFree": false,
      "isDefaultPaid": false
    },
    {
      "id": "usd-pln",
      "base": "USD",
      "quote": "PLN",
      "isDefaultFree": false,
      "isDefaultPaid": false
    },
    {
      "id": "usd-czk",
      "base": "USD",
      "quote": "CZK",
      "isDefaultFree": false,
      "isDefaultPaid": false
    },
    {
      "id": "usd-huf",
      "base": "USD",
      "quote": "HUF",
      "isDefaultFree": false,
      "isDefaultPaid": false
    },
    {
      "id": "usd-ron",
      "base": "USD",
      "quote": "RON",
      "isDefaultFree": false,
      "isDefaultPaid": false
    },
    {
      "id": "usd-ils",
      "base": "USD",
      "quote": "ILS",
      "isDefaultFree": false,
      "isDefaultPaid": false
    },
    {
      "id": "usd-aed",
      "base": "USD",
      "quote": "AED",
      "isDefaultFree": false,
      "isDefaultPaid": false
    },
    {
      "id": "usd-sar",
      "base": "USD",
      "quote": "SAR",
      "isDefaultFree": false,
      "isDefaultPaid": false
    },
    {
      "id": "usd-qar",
      "base": "USD",
      "quote": "QAR",
      "isDefaultFree": false,
      "isDefaultPaid": false
    },
    {
      "id": "usd-kwd",
      "base": "USD",
      "quote": "KWD",
      "isDefaultFree": false,
      "isDefaultPaid": false
    },
    {
      "id": "usd-clp",
      "base": "USD",
      "quote": "CLP",
      "isDefaultFree": false,
      "isDefaultPaid": false
    },
    {
      "id": "usd-cop",
      "base": "USD",
      "quote": "COP",
      "isDefaultFree": false,
      "isDefaultPaid": false
    },
    {
      "id": "usd-pen",
      "base": "USD",
      "quote": "PEN",
      "isDefaultFree": false,
      "isDefaultPaid": false
    },
    {
      "id": "eur-gbp",
      "base": "EUR",
      "quote": "GBP",
      "isDefaultFree": false,
      "isDefaultPaid": false
    },
    {
      "id": "eur-jpy",
      "base": "EUR",
      "quote": "JPY",
      "isDefaultFree": false,
      "isDefaultPaid": false
    },
    {
      "id": "eur-chf",
      "base": "EUR",
      "quote": "CHF",
      "isDefaultFree": false,
      "isDefaultPaid": false
    },
    {
      "id": "eur-cad",
      "base": "EUR",
      "quote": "CAD",
      "isDefaultFree": false,
      "isDefaultPaid": false
    },
    {
      "id": "eur-aud",
      "base": "EUR",
      "quote": "AUD",
      "isDefaultFree": false,
      "isDefaultPaid": false
    },
    {
      "id": "eur-nzd",
      "base": "EUR",
      "quote": "NZD",
      "isDefaultFree": false,
      "isDefaultPaid": false
    },
    {
      "id": "eur-sek",
      "base": "EUR",
      "quote": "SEK",
      "isDefaultFree": false,
      "isDefaultPaid": false
    },
    {
      "id": "eur-nok",
      "base": "EUR",
      "quote": "NOK",
      "isDefaultFree": false,
      "isDefaultPaid": false
    },
    {
      "id": "eur-dkk",
      "base": "EUR",
      "quote": "DKK",
      "isDefaultFree": false,
      "isDefaultPaid": false
    },
    {
      "id": "eur-pln",
      "base": "EUR",
      "quote": "PLN",
      "isDefaultFree": false,
      "isDefaultPaid": false
    },
    {
      "id": "eur-czk",
      "base": "EUR",
      "quote": "CZK",
      "isDefaultFree": false,
      "isDefaultPaid": false
    },
    {
      "id": "eur-huf",
      "base": "EUR",
      "quote": "HUF",
      "isDefaultFree": false,
      "isDefaultPaid": false
    },
    {
      "id": "eur-ron",
      "base": "EUR",
      "quote": "RON",
      "isDefaultFree": false,
      "isDefaultPaid": false
    },
    {
      "id": "eur-try",
      "base": "EUR",
      "quote": "TRY",
      "isDefaultFree": false,
      "isDefaultPaid": false
    },
    {
      "id": "eur-zar",
      "base": "EUR",
      "quote": "ZAR",
      "isDefaultFree": false,
      "isDefaultPaid": false
    },
    {
      "id": "eur-mxn",
      "base": "EUR",
      "quote": "MXN",
      "isDefaultFree": false,
      "isDefaultPaid": false
    },
    {
      "id": "eur-brl",
      "base": "EUR",
      "quote": "BRL",
      "isDefaultFree": false,
      "isDefaultPaid": false
    },
    {
      "id": "eur-cnh",
      "base": "EUR",
      "quote": "CNH",
      "isDefaultFree": false,
      "isDefaultPaid": false
    },
    {
      "id": "eur-cny",
      "base": "EUR",
      "quote": "CNY",
      "isDefaultFree": false,
      "isDefaultPaid": false
    },
    {
      "id": "eur-sgd",
      "base": "EUR",
      "quote": "SGD",
      "isDefaultFree": false,
      "isDefaultPaid": false
    },
    {
      "id": "eur-hkd",
      "base": "EUR",
      "quote": "HKD",
      "isDefaultFree": false,
      "isDefaultPaid": false
    },
    {
      "id": "eur-inr",
      "base": "EUR",
      "quote": "INR",
      "isDefaultFree": false,
      "isDefaultPaid": false
    },
    {
      "id": "eur-ils",
      "base": "EUR",
      "quote": "ILS",
      "isDefaultFree": false,
      "isDefaultPaid": false
    },
    {
      "id": "eur-aed",
      "base": "EUR",
      "quote": "AED",
      "isDefaultFree": false,
      "isDefaultPaid": false
    },
    {
      "id": "gbp-jpy",
      "base": "GBP",
      "quote": "JPY",
      "isDefaultFree": false,
      "isDefaultPaid": false
    },
    {
      "id": "aud-jpy",
      "base": "AUD",
      "quote": "JPY",
      "isDefaultFree": false,
      "isDefaultPaid": false
    },
    {
      "id": "cad-jpy",
      "base": "CAD",
      "quote": "JPY",
      "isDefaultFree": false,
      "isDefaultPaid": false
    },
    {
      "id": "chf-jpy",
      "base": "CHF",
      "quote": "JPY",
      "isDefaultFree": false,
      "isDefaultPaid": false
    },
    {
      "id": "nzd-jpy",
      "base": "NZD",
      "quote": "JPY",
      "isDefaultFree": false,
      "isDefaultPaid": false
    },
    {
      "id": "sek-jpy",
      "base": "SEK",
      "quote": "JPY",
      "isDefaultFree": false,
      "isDefaultPaid": false
    },
    {
      "id": "nok-jpy",
      "base": "NOK",
      "quote": "JPY",
      "isDefaultFree": false,
      "isDefaultPaid": false
    },
    {
      "id": "dkk-jpy",
      "base": "DKK",
      "quote": "JPY",
      "isDefaultFree": false,
      "isDefaultPaid": false
    },
    {
      "id": "pln-jpy",
      "base": "PLN",
      "quote": "JPY",
      "isDefaultFree": false,
      "isDefaultPaid": false
    },
    {
      "id": "czk-jpy",
      "base": "CZK",
      "quote": "JPY",
      "isDefaultFree": false,
      "isDefaultPaid": false
    },
    {
      "id": "huf-jpy",
      "base": "HUF",
      "quote": "JPY",
      "isDefaultFree": false,
      "isDefaultPaid": false
    },
    {
      "id": "try-jpy",
      "base": "TRY",
      "quote": "JPY",
      "isDefaultFree": false,
      "isDefaultPaid": false
    },
    {
      "id": "zar-jpy",
      "base": "ZAR",
      "quote": "JPY",
      "isDefaultFree": false,
      "isDefaultPaid": false
    },
    {
      "id": "mxn-jpy",
      "base": "MXN",
      "quote": "JPY",
      "isDefaultFree": false,
      "isDefaultPaid": false
    },
    {
      "id": "sgd-jpy",
      "base": "SGD",
      "quote": "JPY",
      "isDefaultFree": false,
      "isDefaultPaid": false
    },
    {
      "id": "hkd-jpy",
      "base": "HKD",
      "quote": "JPY",
      "isDefaultFree": false,
      "isDefaultPaid": false
    },
    {
      "id": "cnh-jpy",
      "base": "CNH",
      "quote": "JPY",
      "isDefaultFree": false,
      "isDefaultPaid": false
    },
    {
      "id": "inr-jpy",
      "base": "INR",
      "quote": "JPY",
      "isDefaultFree": false,
      "isDefaultPaid": false
    },
    {
      "id": "gbp-chf",
      "base": "GBP",
      "quote": "CHF",
      "isDefaultFree": false,
      "isDefaultPaid": false
    },
    {
      "id": "gbp-cad",
      "base": "GBP",
      "quote": "CAD",
      "isDefaultFree": false,
      "isDefaultPaid": false
    },
    {
      "id": "gbp-aud",
      "base": "GBP",
      "quote": "AUD",
      "isDefaultFree": false,
      "isDefaultPaid": false
    },
    {
      "id": "gbp-nzd",
      "base": "GBP",
      "quote": "NZD",
      "isDefaultFree": false,
      "isDefaultPaid": false
    },
    {
      "id": "gbp-sek",
      "base": "GBP",
      "quote": "SEK",
      "isDefaultFree": false,
      "isDefaultPaid": false
    },
    {
      "id": "gbp-nok",
      "base": "GBP",
      "quote": "NOK",
      "isDefaultFree": false,
      "isDefaultPaid": false
    },
    {
      "id": "gbp-dkk",
      "base": "GBP",
      "quote": "DKK",
      "isDefaultFree": false,
      "isDefaultPaid": false
    },
    {
      "id": "gbp-pln",
      "base": "GBP",
      "quote": "PLN",
      "isDefaultFree": false,
      "isDefaultPaid": false
    },
    {
      "id": "gbp-czk",
      "base": "GBP",
      "quote": "CZK",
      "isDefaultFree": false,
      "isDefaultPaid": false
    },
    {
      "id": "gbp-huf",
      "base": "GBP",
      "quote": "HUF",
      "isDefaultFree": false,
      "isDefaultPaid": false
    },
    {
      "id": "gbp-try",
      "base": "GBP",
      "quote": "TRY",
      "isDefaultFree": false,
      "isDefaultPaid": false
    },
    {
      "id": "gbp-zar",
      "base": "GBP",
      "quote": "ZAR",
      "isDefaultFree": true,
      "isDefaultPaid": true
    },
    {
      "id": "gbp-sgd",
      "base": "GBP",
      "quote": "SGD",
      "isDefaultFree": false,
      "isDefaultPaid": false
    },
    {
      "id": "gbp-hkd",
      "base": "GBP",
      "quote": "HKD",
      "isDefaultFree": false,
      "isDefaultPaid": false
    },
    {
      "id": "aud-cad",
      "base": "AUD",
      "quote": "CAD",
      "isDefaultFree": false,
      "isDefaultPaid": false
    },
    {
      "id": "aud-nzd",
      "base": "AUD",
      "quote": "NZD",
      "isDefaultFree": false,
      "isDefaultPaid": false
    },
    {
      "id": "cad-chf",
      "base": "CAD",
      "quote": "CHF",
      "isDefaultFree": false,
      "isDefaultPaid": false
    },
    {
      "id": "aud-chf",
      "base": "AUD",
      "quote": "CHF",
      "isDefaultFree": false,
      "isDefaultPaid": false
    },
    {
      "id": "nzd-cad",
      "base": "NZD",
      "quote": "CAD",
      "isDefaultFree": false,
      "isDefaultPaid": false
    },
    {
      "id": "nzd-chf",
      "base": "NZD",
      "quote": "CHF",
      "isDefaultFree": false,
      "isDefaultPaid": false
    },
    {
      "id": "aud-gbp",
      "base": "AUD",
      "quote": "GBP",
      "isDefaultFree": true,
      "isDefaultPaid": true
    },
    {
      "id": "gbp-eur",
      "base": "GBP",
      "quote": "EUR",
      "isDefaultFree": true,
      "isDefaultPaid": true
    }
  ],
  "defaults": [
    "eur-usd",
    "usd-jpy",
    "gbp-usd",
    "usd-cny",
    "usd-brl",
    "gbp-zar",
    "aud-gbp",
    "gbp-eur"
  ]
}